sibutramin/__init__.py
sibutramin_emagrecedor_preco_funciona_emagrece_mesmo-0.0.1.dist-info/LICENSE
sibutramin_emagrecedor_preco_funciona_emagrece_mesmo-0.0.1.dist-info/METADATA
sibutramin_emagrecedor_preco_funciona_emagrece_mesmo-0.0.1.dist-info/WHEEL
sibutramin_emagrecedor_preco_funciona_emagrece_mesmo-0.0.1.dist-info/top_level.txt
sibutramin_emagrecedor_preco_funciona_emagrece_mesmo-0.0.1.dist-info/RECORD
