Metadata-Version: 2.1
Name: sibutramin-emagrecedor-preco-funciona-emagrece-mesmo
Version: 0.0.1
Summary: Veja os resultados que eu tive com o emagrecedor Sibutramin e saiba onde adquiri-lo pelo Menor Preço, com Frete Grátis e Entrega Rápida!
Home-page: https://github.com/pypa/sampleproject
Author: Example Author
Author-email: author@example.com
License: UNKNOWN
Project-URL: Bug Tracker, https://github.com/pypa/sampleproject/issues
Platform: UNKNOWN
Classifier: Programming Language :: Python :: 3
Classifier: License :: OSI Approved :: MIT License
Classifier: Operating System :: OS Independent
Requires-Python: >=3.6
License-File: LICENSE
